odoo/addons/account_statement_import_online_ponto_ing/README.rst
odoo/addons/account_statement_import_online_ponto_ing/__init__.py
odoo/addons/account_statement_import_online_ponto_ing/__manifest__.py
odoo/addons/account_statement_import_online_ponto_ing/i18n/account_statement_import_online_ponto_ing.pot
odoo/addons/account_statement_import_online_ponto_ing/i18n/es.po
odoo/addons/account_statement_import_online_ponto_ing/i18n/it.po
odoo/addons/account_statement_import_online_ponto_ing/models/__init__.py
odoo/addons/account_statement_import_online_ponto_ing/models/online_bank_statement_provider_ponto.py
odoo/addons/account_statement_import_online_ponto_ing/readme/CONFIGURE.rst
odoo/addons/account_statement_import_online_ponto_ing/readme/CONTRIBUTORS.rst
odoo/addons/account_statement_import_online_ponto_ing/readme/DESCRIPTION.rst
odoo/addons/account_statement_import_online_ponto_ing/static/description/icon.png
odoo/addons/account_statement_import_online_ponto_ing/static/description/index.html
odoo14_addon_account_statement_import_online_ponto_ing-14.0.1.0.1.dev10.dist-info/METADATA
odoo14_addon_account_statement_import_online_ponto_ing-14.0.1.0.1.dev10.dist-info/WHEEL
odoo14_addon_account_statement_import_online_ponto_ing-14.0.1.0.1.dev10.dist-info/top_level.txt
odoo14_addon_account_statement_import_online_ponto_ing-14.0.1.0.1.dev10.dist-info/RECORD
